Workbook

Sheet 表紙
O8: LMS学習管理システム
O9: 体験型Java研修
S11: メッセージ一覧
X15: ="第"&TEXT(MAX(更新履歴!A8:J157),"#0.0")&"版" -> 第1.3版 | AA15: =MAX(更新履歴!K8:T157) -> 45268
U18: 作成者 | Z18: 審査者 | AE18: 承認者
U19: 加藤

Sheet 更新履歴
A1: プロジェクト名 | K1: システム名 | U1: =表紙!S11 -> メッセージ一覧 | AO1: 作成者 | AU1: 作成日 | BA1: 更新者 | BG1: 更新日
A2: =表紙!O9 -> 体験型Java研修 | K2: =表紙!O8 -> LMS学習管理システム | U2: 更新履歴 | AO2: 加藤 | AU2: 44265 | BA2: 堀井 | BG2: 45268
A5: バージョン | K5: 日付 | U5: 章番号 | Y5: 内容 | BA5: 作成者 / 更新者
A8: 1 | K8: 44161 | U8: 全て | Y8: 新規作成 | BA8: 加藤
A11: 1.1 | K11: 44292 | U11: エラーメッセージ一覧（入力チェック） | Y11: シート追加 ・エラーメッセージ一覧（入力チェック） | BA11: 臼井
A14: 1.3 | K14: 45268 | U14: 全て | Y14: 最新の状態に合わせて追加削除 | BA14: 堀井

Sheet メッセージ一覧
A1: プロジェクト名 | J1: システム名 | R1: =表紙!S11 -> メッセージ一覧 | AJ1: 作成者 | AO1: 作成日 | AT1: 更新者 | AY1: 更新日
A2: =表紙!O9 -> 体験型Java研修 | J2: =表紙!O8 -> LMS学習管理システム | R2: メッセージ一覧 | AJ2: 加藤 | AO2: 44265 | AT2: 堀井 | AY2: 45268
A4: messages.properties
A5: No. | C5: メッセージID | M5: メッセージ内容 | AK5: 備考 | AP5: 備考
A6: =MAX(A$5:INDIRECT("A"&ROW()-1))+1 -> 1 | C6: mail.contract.subject | M6: 【東京ITスクール】ご契約内容の送付
A7: =MAX(A$5:INDIRECT("A"&ROW()-1))+1 -> 2 | C7: mail.contract.body | M7: お世話になっております。\n\n株式会社システムシェアード\n東京ITスクール運営事務局でございます。 \n\n以下の内容で契約を締結致しました。\nご確認頂きます様お願い致します。\n\n【契約内容】\n:contract:\n\n【個人情報利用目的】\n:personal:\n\n※このメールにお心当たりがない場合はご破棄くださいますようお願い致します。\n※このメールはサーバより自動送信しておりますため、ご返信頂いてもお答えできません。\nお問い合わせは、itsup@3sss.co.jpまでお願い致します。
A8: =MAX(A$5:INDIRECT("A"&ROW()-1))+1 -> 3 | C8: mail.resetpass.subject | M8: 【LMS学習管理システム】パスワード再設定手続きのお知らせ
A9: =MAX(A$5:INDIRECT("A"&ROW()-1))+1 -> 4 | C9: mail.resetpass.body | M9: LMSをご利用いただきありがとうございます。\n\nユーザのパスワード変更を受け付けました。\n下記URLにアクセス後、新規にパスワードを設定してください。\n\n:url:\n\n※このメールにお心当たりがない場合はご破棄くださいますようお願い致します。\n※このメールはサーバより自動送信しておりますため、ご返信頂いてもお答えできません。\nお問い合わせは、itsup@3sss.co.jpまでお願い致します。
A10: =MAX(A$5:INDIRECT("A"&ROW()-1))+1 -> 5 | C10: mail.logininfo.subject | M10: 【LMS学習管理システム】ログイン情報の送付
A11: =MAX(A$5:INDIRECT("A"&ROW()-1))+1 -> 6 | C11: mail.logininfo.body | M11: LMSをご利用いただきありがとうございます。\nログイン情報を発行しました。以下の認証情報を利用してログインしてください。\n\nLMS学習管理システムURL：:url:\nログインID：:login_id:\nパスワード：:password:\n\n※このメールにお心当たりがない場合はご破棄くださいますようお願い致します。\n※このメールはサーバより自動送信しておりますため、ご返信頂いてもお答えできません。\nお問い合わせは、itsup@3sss.co.jpまでお願い致します。
A12: =MAX(A$5:INDIRECT("A"&ROW()-1))+1 -> 7 | C12: mail.mailfailed.subject | M12: 【LMS】メールの送信に失敗しています。
A13: =MAX(A$5:INDIRECT("A"&ROW()-1))+1 -> 8 | C13: mail.mailfailed.body | M13: LMSをご利用いただきありがとうございます。\n\nメールの送信に失敗しているデータがあります。\nシステム管理者にお問い合わせください。\n\nメールアドレス：:mail_address:\n件名：:subject:\n送信予約日時：:que_create_date:\n\n※このメールにお心当たりがない場合はご破棄くださいますようお願い致します。\n※このメールはサーバより自動送信しておりますため、ご返信頂いてもお答えできません。\nお問い合わせは、itsup@3sss.co.jpまでお願い致します。
A14: =MAX(A$5:INDIRECT("A"&ROW()-1))+1 -> 9 | C14: attendance.update.notice | M14: 勤怠情報の登録が完了しました。
A15: =MAX(A$5:INDIRECT("A"&ROW()-1))+1 -> 10 | C15: attendance.punchAlreadyExists | M15: 本日の勤怠情報は既に入力されています。直接編集してください。
A16: =MAX(A$5:INDIRECT("A"&ROW()-1))+1 -> 11 | C16: attendance.punchInEmpty | M16: 出勤情報がないため退勤情報を入力出来ません。
A17: =MAX(A$5:INDIRECT("A"&ROW()-1))+1 -> 12 | C17: attendance.company.joseiKinInfoIsNotExists | M17: 対象ユーザの企業は助成金情報が未入力のため、画面を表示することができません。
... A39: =MAX(A$5:INDIRECT("A"&ROW()-1))+1 -> 34 | C39: fileShare.fileShareFlg | M39: 貴社はファイル共有機能の使用が許可されていません。

Sheet エラーメッセージ一覧
A1: プロジェクト名 | J1: システム名 | R1: =表紙!S11 -> メッセージ一覧 | AJ1: 作成者 | AO1: 作成日 | AT1: 更新者 | AY1: 更新日
A2: =表紙!O9 -> 体験型Java研修 | J2: =表紙!O8 -> LMS学習管理システム | R2: エラーメッセージ一覧 | AJ2: 加藤 | AO2: 44265 | AT2: 堀井 | AY2: 45268
A4: errors.properties
A5: No. | C5: メッセージID | M5: メッセージ内容 | AK5: 備考 | AP5: 備考
A6: =MAX(A$5:INDIRECT("A"&ROW()-1))+1 -> 1 | C6: header | M6: <ul style="padding-left:0;list-style:none;">
A7: =MAX(A$5:INDIRECT("A"&ROW()-1))+1 -> 2 | C7: footer | M7: </ul>
A8: =MAX(A$5:INDIRECT("A"&ROW()-1))+1 -> 3 | C8: prefix | M8: <li><span class="help-inline error">*&nbsp;
A9: =MAX(A$5:INDIRECT("A"&ROW()-1))+1 -> 4 | C9: suffix | M9: </span></li>
A10: =MAX(A$5:INDIRECT("A"&ROW()-1))+1 -> 5 | C10: invalid | M10: {0}が不正です。
A11: =MAX(A$5:INDIRECT("A"&ROW()-1))+1 -> 6 | C11: maxlength | M11: {0}の長さが最大値({1})を超えています。
A12: =MAX(A$5:INDIRECT("A"&ROW()-1))+1 -> 7 | C12: minlength | M12: {0}の長さが最小値({1})未満です。
A13: =MAX(A$5:INDIRECT("A"&ROW()-1))+1 -> 8 | C13: maxval | M13: {0}の値が最大値({1})を超えています。
A14: =MAX(A$5:INDIRECT("A"&ROW()-1))+1 -> 9 | C14: maxvalBulk | M14: {0}：{1}が最大値({2})を超えています。
A15: =MAX(A$5:INDIRECT("A"&ROW()-1))+1 -> 10 | C15: minval | M15: {0}の値が最小値({1})未満です。
A16: =MAX(A$5:INDIRECT("A"&ROW()-1))+1 -> 11 | C16: maxbytelength | M16: {0}のバイト長が最大値({1})を超えています。
A17: =MAX(A$5:INDIRECT("A"&ROW()-1))+1 -> 12 | C17: minbytelength | M17: {0}のバイト長が最小値({1})未満です。
... A168: =MAX(A$5:INDIRECT("A"&ROW()-1))+1 -> 163 | C168: password.updateFailed | M168: パスワードの更新に失敗しました。

Sheet エラーメッセージ一覧（入力チェック）
A1: プロジェクト名 | J1: システム名 | R1: =表紙!S11 -> メッセージ一覧 | AJ1: 作成者 | AO1: 作成日 | AT1: 更新者 | AY1: 更新日
A2: =表紙!O9 -> 体験型Java研修 | J2: =表紙!O8 -> LMS学習管理システム | R2: メッセージ一覧 | AJ2: 臼井 | AO2: 44292 | AT2: 堀井 | AY2: 45268
A4: ValidationMessages.properties
A5: No. | C5: メッセージID | Q5: メッセージ内容 | AK5: 備考 | AP5: 備考
A6: =MAX(A$5:INDIRECT("A"&ROW()-1))+1 -> 1 | C6: jakarta.validation.constraints.NotBlank.message | Q6: {0}は必須です。
A7: =MAX(A$5:INDIRECT("A"&ROW()-1))+1 -> 2 | C7: jakarta.validation.constraints.NotNull.message | Q7: {0}は必須です。
A8: =MAX(A$5:INDIRECT("A"&ROW()-1))+1 -> 3 | C8: jakarta.validation.constraints.Size.message | Q8: {0}の長さが最大値({max})を超えています。
A9: =MAX(A$5:INDIRECT("A"&ROW()-1))+1 -> 4 | C9: jakarta.validation.constraints.Max.message | Q9: {0}の値が最大値({1})を超えています。
A10: =MAX(A$5:INDIRECT("A"&ROW()-1))+1 -> 5 | C10: jakarta.validation.constraints.Min.message | Q10: {0}の値が最小値({1})未満です。
A11: =MAX(A$5:INDIRECT("A"&ROW()-1))+1 -> 6 | C11: jakarta.validation.constraints.Email.message | Q11: {0}はメールアドレスとして不正です。
A12: =MAX(A$5:INDIRECT("A"&ROW()-1))+1 -> 7 | C12: org.hibernate.validator.constraints.Range.message | Q12: {0}は{min}と{max}の間でなければいけません。
A13: =MAX(A$5:INDIRECT("A"&ROW()-1))+1 -> 8 | C13: pattern.password | Q13: 「パスワード」には半角英数字のみ使用可能です。また、半角英大文字、半角英小文字、数字を含めた8～20文字を入力してください。
A14: =MAX(A$5:INDIRECT("A"&ROW()-1))+1 -> 9 | C14: pattern.invalid | Q14: {0}が不正です。

Sheet ラベル一覧
A1: プロジェクト名 | J1: システム名 | R1: =表紙!S11 -> メッセージ一覧 | AJ1: 作成者 | AO1: 作成日 | AT1: 更新者 | AY1: 更新日
A2: =表紙!O9 -> 体験型Java研修 | J2: =表紙!O8 -> LMS学習管理システム | R2: ラベル一覧 | AJ2: 加藤 | AO2: 44265 | AT2: 堀井 | AY2: 45268
A4: messages.properties
A5: No. | C5: ラベルID | M5: ラベル内容 | AK5: 備考 | AP5: 備考
A6: =MAX(A$5:INDIRECT("A"&ROW()-1))+1 -> 1 | C6: user | M6: ユーザー
A7: =MAX(A$5:INDIRECT("A"&ROW()-1))+1 -> 2 | C7: lmsUser | M7: ユーザー
A8: =MAX(A$5:INDIRECT("A"&ROW()-1))+1 -> 3 | C8: company | M8: 企業
A9: =MAX(A$5:INDIRECT("A"&ROW()-1))+1 -> 4 | C9: userCompany | M9: 送信先の企業担当者
A10: =MAX(A$5:INDIRECT("A"&ROW()-1))+1 -> 5 | C10: companyData | M10: 企業データ
A11: =MAX(A$5:INDIRECT("A"&ROW()-1))+1 -> 6 | C11: place | M11: 会場
A12: =MAX(A$5:INDIRECT("A"&ROW()-1))+1 -> 7 | C12: course | M12: コース
A13: =MAX(A$5:INDIRECT("A"&ROW()-1))+1 -> 8 | C13: section | M13: セクション
A14: =MAX(A$5:INDIRECT("A"&ROW()-1))+1 -> 9 | C14: category | M14: カテゴリ
A15: =MAX(A$5:INDIRECT("A"&ROW()-1))+1 -> 10 | C15: genre | M15: 試験カテゴリ
A16: =MAX(A$5:INDIRECT("A"&ROW()-1))+1 -> 11 | C16: genre.detail | M16: 詳細試験カテゴリ
A17: =MAX(A$5:INDIRECT("A"&ROW()-1))+1 -> 12 | C17: exam | M17: 試験
... A263: =MAX(A$5:INDIRECT("A"&ROW()-1))+1 -> 258 | C263: faqCategoryName | M263: 質問カテゴリー名
